LICENSE
MANIFEST.in
README.md
setup.py
ssdk/__init__.py
ssdk/config.py
ssdk/manifest.py
ssdk/cli/__init__.py
ssdk/cli/lib.py
ssdk/cli/ssdk.py
ssdk/core/__init__.py
ssdk/core/models.py
ssdk/core/utils.py
steam_scheduled_download_killer.egg-info/PKG-INFO
steam_scheduled_download_killer.egg-info/SOURCES.txt
steam_scheduled_download_killer.egg-info/dependency_links.txt
steam_scheduled_download_killer.egg-info/entry_points.txt
steam_scheduled_download_killer.egg-info/top_level.txt