Metadata-Version: 2.1
Name: steam-scheduled-download-killer
Version: 0.0.1
Summary: Set update priority for all Steam games to avoid scheduled downloads.
Home-page: https://github.com/vlntnwbr/ssdk
Author: Valentin Weber
Author-email: dev@vweber.eu
Maintainer: Valentin Weber
Maintainer-email: dev@vweber.eu
License: EUPL
Project-URL: Bug Tracker, https://github.com/vlntnwbr/ssdk/issues?q=label%3bug
Platform: windows
Classifier: Development Status :: 1 - Planning
Classifier: Environment :: Console
Classifier: Intended Audience :: End Users/Desktop
Classifier: Intended Audience :: Other Audience
Classifier: License :: OSI Approved :: European Union Public Licence 1.2 (EUPL 1.2)
Classifier: Operating System :: Microsoft :: Windows :: Windows 10
Classifier: Programming Language :: Python :: 3 :: Only
Classifier: Topic :: Desktop Environment :: File Managers
Classifier: Topic :: Games/Entertainment
Classifier: Topic :: Utilities
Requires-Python: >=3.9
License-File: LICENSE
